aiowebsocket/__init__.py
aiowebsocket/converses.py
aiowebsocket/enumerations.py
aiowebsocket/exceptions.py
aiowebsocket/freams.py
aiowebsocket/handshakes.py
aiowebsocket/parts.py
aiowebsocket-1.0.0.dev1.dist-info/METADATA
aiowebsocket-1.0.0.dev1.dist-info/RECORD
aiowebsocket-1.0.0.dev1.dist-info/WHEEL
aiowebsocket-1.0.0.dev1.dist-info/top_level.txt
